roscopilot/__init__.py
roscopilot/hello_world.py
roscopilot-0.0.0.dist-info/LICENSE
roscopilot-0.0.0.dist-info/METADATA
roscopilot-0.0.0.dist-info/WHEEL
roscopilot-0.0.0.dist-info/top_level.txt
roscopilot-0.0.0.dist-info/RECORD
